RestrictedPython/Eval.py
RestrictedPython/Guards.py
RestrictedPython/Limits.py
RestrictedPython/PrintCollector.py
RestrictedPython/Utilities.py
RestrictedPython/__init__.py
RestrictedPython/_compat.py
RestrictedPython/compile.py
RestrictedPython/transformer.py
RestrictedPython-7.4.dist-info/LICENSE.txt
RestrictedPython-7.4.dist-info/METADATA
RestrictedPython-7.4.dist-info/WHEEL
RestrictedPython-7.4.dist-info/top_level.txt
RestrictedPython-7.4.dist-info/RECORD
