Metadata-Version: 2.1
Name: RestrictedPython
Version: 7.4
Summary: RestrictedPython is a defined subset of the Python language which allows to provide a program input into a trusted environment.
Home-page: https://github.com/zopefoundation/RestrictedPython
Author: Zope Foundation and Contributors
Author-email: zope-dev@zope.dev
License: ZPL 2.1
Project-URL: Documentation, https://restrictedpython.readthedocs.io/
Project-URL: Source, https://github.com/zopefoundation/RestrictedPython
Project-URL: Tracker, https://github.com/zopefoundation/RestrictedPython/issues
Keywords: restricted execution security untrusted code
Classifier: Development Status :: 6 - Mature
Classifier: License :: OSI Approved :: Zope Public License
Classifier: Programming Language :: Python
Classifier: Operating System :: OS Independent
Classifier: Programming Language :: Python :: 3
Classifier: Programming Language :: Python :: 3.8
Classifier: Programming Language :: Python :: 3.9
Classifier: Programming Language :: Python :: 3.10
Classifier: Programming Language :: Python :: 3.11
Classifier: Programming Language :: Python :: 3.12
Classifier: Programming Language :: Python :: 3.13
Classifier: Programming Language :: Python :: Implementation :: CPython
Classifier: Topic :: Security
Requires-Python: >=3.8, <3.14
License-File: LICENSE.txt
Provides-Extra: test
Requires-Dist: pytest; extra == "test"
Requires-Dist: pytest-mock; extra == "test"
Provides-Extra: docs
Requires-Dist: Sphinx; extra == "docs"
Requires-Dist: furo; extra == "docs"
